web_raider/__init__.py
web_raider/article.py
web_raider/assets/__init__.py
web_raider/assets/key_import.py
web_raider/assets/prompts.py
web_raider/codebase.py
web_raider/connection_manager.py
web_raider/constants.py
web_raider/evaluate.py
web_raider/forums.py
web_raider/model_calls.py
web_raider/pipeline.py
web_raider/search.py
web_raider/shortlist.py
web_raider/url_classifier.py
web_raider/utils.py
web_raider-0.1.0.dist-info/entry_points.txt
web_raider-0.1.0.dist-info/METADATA
web_raider-0.1.0.dist-info/WHEEL
web_raider-0.1.0.dist-info/RECORD
