Metadata-Version: 2.1
Name: web-raider
Version: 0.1.0
Summary: Web Raider
Home-page: https://github.com/ThePyProgrammer/web-raider
Author: Prannaya
Author-email: prannayagupta@gmail.com
Requires-Python: >=3.9,<4.0
Classifier: Programming Language :: Python :: 3
Classifier: Programming Language :: Python :: 3.9
Classifier: Programming Language :: Python :: 3.10
Classifier: Programming Language :: Python :: 3.11
Classifier: Programming Language :: Python :: 3.12
Requires-Dist: boto3 (>=1.35.22,<2.0.0)
Requires-Dist: bs4 (>=0.0.2,<0.0.3)
Requires-Dist: fastapi (>=0.115.0,<0.116.0)
Requires-Dist: googlesearch-python (>=1.2.5,<2.0.0)
Requires-Dist: litellm (>=1.46.6,<2.0.0)
Requires-Dist: lxml[html-clean] (>=5.3.0,<6.0.0)
Requires-Dist: newspaper3k (>=0.2.8,<0.3.0)
Requires-Dist: pandas (>=2.2.2,<3.0.0)
Requires-Dist: requests (>=2.32.3,<3.0.0)
Requires-Dist: scikit-learn (>=1.5.1,<2.0.0)
Requires-Dist: uvicorn (>=0.30.6,<0.31.0)
Requires-Dist: websockets (>=13.1,<14.0)
Project-URL: Repository, https://github.com/ThePyProgrammer/web-raider
